django_countries/__init__.py
django_countries/base.py
django_countries/conf.py
django_countries/data.py
django_countries/fields.py
django_countries/filters.py
django_countries/ioc_data.py
django_countries/makesprite.py
django_countries/models.py
django_countries/release.py
django_countries/serializer_fields.py
django_countries/serializers.py
django_countries/utils.py
django_countries/widgets.py
django_countries/datasets/geoip2/GeoLite2-Country.mmdb
django_countries/locale/ar/LC_MESSAGES/django.mo
django_countries/locale/ar/LC_MESSAGES/django.po
django_countries/locale/bg/LC_MESSAGES/django.mo
django_countries/locale/bg/LC_MESSAGES/django.po
django_countries/locale/ca/LC_MESSAGES/django.mo
django_countries/locale/ca/LC_MESSAGES/django.po
django_countries/locale/cs/LC_MESSAGES/django.mo
django_countries/locale/cs/LC_MESSAGES/django.po
django_countries/locale/de/LC_MESSAGES/django.mo
django_countries/locale/de/LC_MESSAGES/django.po
django_countries/locale/el/LC_MESSAGES/django.mo
django_countries/locale/el/LC_MESSAGES/django.po
django_countries/locale/en/LC_MESSAGES/django.mo
django_countries/locale/en/LC_MESSAGES/django.po
django_countries/locale/eo/LC_MESSAGES/django.mo
django_countries/locale/eo/LC_MESSAGES/django.po
django_countries/locale/es/LC_MESSAGES/django.mo
django_countries/locale/es/LC_MESSAGES/django.po
django_countries/locale/et/LC_MESSAGES/django.mo
django_countries/locale/et/LC_MESSAGES/django.po
django_countries/locale/eu/LC_MESSAGES/django.mo
django_countries/locale/eu/LC_MESSAGES/django.po
django_countries/locale/eu_ES/LC_MESSAGES/django.mo
django_countries/locale/eu_ES/LC_MESSAGES/django.po
django_countries/locale/fa/LC_MESSAGES/django.mo
django_countries/locale/fa/LC_MESSAGES/django.po
django_countries/locale/fi/LC_MESSAGES/django.mo
django_countries/locale/fi/LC_MESSAGES/django.po
django_countries/locale/fr/LC_MESSAGES/django.mo
django_countries/locale/fr/LC_MESSAGES/django.po
django_countries/locale/he/LC_MESSAGES/django.mo
django_countries_with_calling_codes-0.1.1.dist-info/LICENSE
django_countries_with_calling_codes-0.1.1.dist-info/METADATA
django_countries_with_calling_codes-0.1.1.dist-info/WHEEL
django_countries_with_calling_codes-0.1.1.dist-info/top_level.txt
django_countries_with_calling_codes-0.1.1.dist-info/RECORD
