Metadata-Version: 1.1
Name: django-countries-with-calling-codes
Version: 0.1.1
Summary: Django-countries fork with calling codes and geoip2 integration added
Home-page: https://github.com/rondebu/django-countries-with-calling-codes
Author: Rondebu Software
Author-email: info@rondebu.com
License: MIT
Platform: UNKNOWN
Classifier: Environment :: Web Environment
Classifier: Framework :: Django
Classifier: Intended Audience :: Developers
Classifier: License :: OSI Approved :: MIT License
Classifier: Operating System :: OS Independent
Classifier: Programming Language :: Python
Classifier: Programming Language :: Python :: 3.5
Classifier: Programming Language :: Python :: 3.6
Classifier: Framework :: Django
Classifier: Topic :: Internet :: WWW/HTTP
Classifier: Topic :: Internet :: WWW/HTTP :: Dynamic Content
